setup.py
ehvagrant/__init__.py
ehvagrant/ehvagrant.py
ehvagrant.egg-info/PKG-INFO
ehvagrant.egg-info/SOURCES.txt
ehvagrant.egg-info/dependency_links.txt
ehvagrant.egg-info/entry_points.txt
ehvagrant.egg-info/not-zip-safe
ehvagrant.egg-info/requires.txt
ehvagrant.egg-info/top_level.txt