Metadata-Version: 1.0
Name: ehvagrant
Version: 0.1
Summary: enhanced Vagrant with importable python module
Home-page: https://github.com/kimballXD/ehvagrant
Author: Kimball Wu
Author-email: kimballXD@gmail.com
License: MIT
Platform: UNKNOWN
